pycalc/__init__.py
pycalc/__main__.py
pycalc/calcClass.py
heakl_pycalc-0.0.1.dist-info/METADATA
heakl_pycalc-0.0.1.dist-info/WHEEL
heakl_pycalc-0.0.1.dist-info/entry_points.txt
heakl_pycalc-0.0.1.dist-info/top_level.txt
heakl_pycalc-0.0.1.dist-info/RECORD
